splurge_lazyframe_compare/__init__.py
splurge_lazyframe_compare/__main__.py
splurge_lazyframe_compare/cli.py
splurge_lazyframe_compare/core/__init__.py
splurge_lazyframe_compare/core/comparator.py
splurge_lazyframe_compare/exceptions/__init__.py
splurge_lazyframe_compare/exceptions/comparison_exceptions.py
splurge_lazyframe_compare/models/__init__.py
splurge_lazyframe_compare/models/comparison.py
splurge_lazyframe_compare/models/schema.py
splurge_lazyframe_compare/models/validation.py
splurge_lazyframe_compare/services/__init__.py
splurge_lazyframe_compare/services/base_service.py
splurge_lazyframe_compare/services/comparison_service.py
splurge_lazyframe_compare/services/orchestrator.py
splurge_lazyframe_compare/services/preparation_service.py
splurge_lazyframe_compare/services/reporting_service.py
splurge_lazyframe_compare/services/validation_service.py
splurge_lazyframe_compare/utils/__init__.py
splurge_lazyframe_compare/utils/config_helpers.py
splurge_lazyframe_compare/utils/constants.py
splurge_lazyframe_compare/utils/data_helpers.py
splurge_lazyframe_compare/utils/file_operations.py
splurge_lazyframe_compare/utils/formatting.py
splurge_lazyframe_compare/utils/logging_helpers.py
splurge_lazyframe_compare/utils/type_helpers.py
splurge_lazyframe_compare/validators/__init__.py
splurge_lazyframe_compare-2025.3.1.dist-info/licenses/LICENSE
splurge_lazyframe_compare-2025.3.1.dist-info/METADATA
splurge_lazyframe_compare-2025.3.1.dist-info/WHEEL
splurge_lazyframe_compare-2025.3.1.dist-info/entry_points.txt
splurge_lazyframe_compare-2025.3.1.dist-info/top_level.txt
splurge_lazyframe_compare-2025.3.1.dist-info/RECORD
